jsonql_sqlalchemy/__init__.py
jsonql_sqlalchemy/query.py
jsonql_sqlalchemy/types.py
jsonql_sqlalchemy/utils.py
jsonql_sqlalchemy-1.0.1.dist-info/DESCRIPTION.rst
jsonql_sqlalchemy-1.0.1.dist-info/METADATA
jsonql_sqlalchemy-1.0.1.dist-info/RECORD
jsonql_sqlalchemy-1.0.1.dist-info/WHEEL
jsonql_sqlalchemy-1.0.1.dist-info/metadata.json
jsonql_sqlalchemy-1.0.1.dist-info/top_level.txt
